<Properties StartupConfiguration="{D22B8647-4C15-C0CF-A246-59B4651124D0}|">
  <MonoDevelop.Ide.Workbench ActiveDocument="Assets/Scripts/Bin.cs">
    <Files>
      <File FileName="Assets/Scripts/playerMovement.cs" Line="35" Column="1" />
      <File FileName="Assets/Scripts/Bin.cs" Line="42" Column="47" />
    </Files>
  </MonoDevelop.Ide.Workbench>
  <MonoDevelop.Ide.DebuggingService.PinnedWatches />
  <MonoDevelop.Ide.Workspace ActiveConfiguration="Debug" />
  <MonoDevelop.Ide.ItemProperties.Assembly-CSharp PreferredExecutionTarget="Unity.Editor" />
  <MonoDevelop.Ide.DebuggingService.Breakpoints>
    <BreakpointStore />
  </MonoDevelop.Ide.DebuggingService.Breakpoints>
  <MultiItemStartupConfigurations />
</Properties>